uxdiff.py
uxdiff-1.5.2.data/scripts/uxdiff
uxdiff-1.5.2.dist-info/LICENSE
uxdiff-1.5.2.dist-info/METADATA
uxdiff-1.5.2.dist-info/WHEEL
uxdiff-1.5.2.dist-info/top_level.txt
uxdiff-1.5.2.dist-info/RECORD
