Metadata-Version: 2.1
Name: uxdiff
Version: 1.5.2
Summary: As a command, Compare two text files or directories. As a module, Compare two sequences of hashable objects.
Home-page: https://github.com/tanaga9/uxdiff
Author: Tanaga
Author-email: tanaga9@users.noreply.github.com
License: MIT
Keywords: colored side-by-side diff
Classifier: Development Status :: 5 - Production/Stable
Classifier: Environment :: Console
Classifier: License :: OSI Approved :: MIT License
Classifier: Topic :: Text Processing
Classifier: Programming Language :: Python :: 2
Classifier: Programming Language :: Python :: 2.7
Classifier: Programming Language :: Python :: 3
Classifier: Programming Language :: Python :: 3.5
Classifier: Programming Language :: Python :: 3.6
Classifier: Programming Language :: Python :: 3.7
Classifier: Programming Language :: Python :: 3.8
Classifier: Programming Language :: Python :: 3.9
Classifier: Programming Language :: Python :: 3.10
Classifier: Programming Language :: Python :: 3.11
License-File: LICENSE
Requires-Dist: unidiff >=0.6.0
